{
  "facebook": {
    "exchangeUrl": "https://graph.facebook.com/oauth/access_token",
    "data":{
      "client_id": "625011864281657",
      "client_secret": "9de3bc6cc8120daa12a00f4fc923f3bb",
      "redirect_uri":"https://dev.zzbase.com/facebook/oauthhandler",
      "grant_type": "authorization_code"
    }
  },
  "google": {
    "exchangeUrl": "https://accounts.google.com/o/oauth2/token",
    "data":{
      "client_id": "887090077504-fb8nqtvt4t528rptkfo4cua4kp1pipuo.apps.googleusercontent.com",
      "client_secret": "hLKMioxgs_s5eWhGjy5lld02",
      "grant_type": "authorization_code",
      "redirect_uri": "http://localhost:3000/google/oauthhandler"
    }
  },
  "dropbox": {
    "exchangeUrl": "https://api.dropbox.com/1/oauth2/token",
    "data":{
      "client_id": "tb1iup9uvr0w3qw",
      "client_secret": "609q6cboxeguy8j",
      "redirect_uri": "https://dev.zzbase.com/dropbox/oauthhandler",
      "grant_type": "authorization_code"
    }
  },
  "basecamp": {
    "exchangeUrl": "https://launchpad.37signals.com/authorization/token",
    "data":{
      "client_id": "92deafd2b20b0d8893ca8ec22280fa8785168304",
      "client_secret": "ae104a4614ab8ba259837b885c3e2f17013a5b9d",
      "redirect_uri": "http://localhost:3000/basecamp/oauthhandler",
      "type": "web_server",
      "grant_type": "authorization_code"
    }
  }
}
